simple_image_viewer/__init__.py
simple_image_viewer/flowlib.py
simple_image_viewer/helpers.py
simple_image_viewer/pfmutil.py
simple_image_viewer/simple_image_viewer.py
simple_image_viewer/sintel_io.py
simple_image_viewer-0.1.0.dist-info/LICENSE
simple_image_viewer-0.1.0.dist-info/METADATA
simple_image_viewer-0.1.0.dist-info/WHEEL
simple_image_viewer-0.1.0.dist-info/top_level.txt
simple_image_viewer-0.1.0.dist-info/RECORD
