Metadata-Version: 2.1
Name: simple-image-viewer
Version: 0.1.0
Summary: A simple image viewer for computer vision purposes.
Home-page: https://github.com/saeid-h/Simple-Image-Viewer
Author: Saeid Hosseinipoor
Author-email: shossei1@stevens.edu
License: UNKNOWN
Platform: UNKNOWN
Classifier: Programming Language :: Python :: 2.7
Classifier: License :: OSI Approved :: MIT License
Classifier: Operating System :: OS Independent
Requires-Python: >=2.7
